LICENSE
MANIFEST.in
README.rst
requirements.txt
requirements_dev.txt
setup.cfg
setup.py
biokit/__init__.py
biokit.egg-info/PKG-INFO
biokit.egg-info/SOURCES.txt
biokit.egg-info/dependency_links.txt
biokit.egg-info/entry_points.txt
biokit.egg-info/not-zip-safe
biokit.egg-info/requires.txt
biokit.egg-info/top_level.txt
biokit/data/__init__.py
biokit/data/test_heatmap.csv
biokit/data/converters/1_R1_.fastq.gz
biokit/data/converters/1_R2_.fastq.gz
biokit/data/converters/R1R2_from_bam.fasta
biokit/data/converters/R1R2_from_bam.fastq
biokit/data/converters/README.rst
biokit/data/converters/__init__.py
biokit/data/converters/measles.bam
biokit/data/converters/measles.bed.gz
biokit/data/converters/measles.sorted.bam
biokit/data/converters/sample_v2.fasta
biokit/data/converters/sample_v2.fastq
biokit/data/converters/sample_v2.scf
biokit/data/converters/sample_v3.fasta
biokit/data/converters/sample_v3.fastq
biokit/data/converters/sample_v3.scf
biokit/data/converters/test1.vcf
biokit/data/converters/test_fasta_1.fasta
biokit/data/converters/test_fastq_1.fastq
biokit/dev/__init__.py
biokit/dev/mpl_focus.py
biokit/goid/__init__.py
biokit/goid/godb.py
biokit/network/__init__.py
biokit/network/complexes.py
biokit/rtools/__init__.py
biokit/rtools/package.py
biokit/rtools/py2r.py
biokit/rtools/pyper.py
biokit/rtools/r4python.py
biokit/rtools/session.py
biokit/rtools/tools.py
biokit/sequence/__init__.py
biokit/sequence/dna.py
biokit/sequence/iupac.py
biokit/sequence/peptide.py
biokit/sequence/rna.py
biokit/sequence/seq.py
biokit/stats/__init__.py
biokit/stats/criteria.py
biokit/stats/kde.py
biokit/stats/mixture.py
biokit/taxonomy/__init__.py
biokit/taxonomy/taxonomy.py
biokit/viz/__init__.py
biokit/viz/anova.py
biokit/viz/boxplot.py
biokit/viz/core.py
biokit/viz/corrplot.py
biokit/viz/heatmap.py
biokit/viz/hinton.py
biokit/viz/hist2d.py
biokit/viz/imshow.py
biokit/viz/linkage.py
biokit/viz/mpl.py
biokit/viz/scatter.py
biokit/viz/volcano.py
examples/README.txt
examples/plot_corrplot.py
examples/plot_hist2d.py
examples/plot_mixture.py
examples/plot_scatter.py