Metadata-Version: 2.1
Name: biokit
Version: 0.5.0
Summary: Set of tools related to Bioinformatics (e.g., visualisation)
Home-page: http://github.com/biokit/biokit
Author: Thomas Cokelaer
Author-email: cokelaer@gmail.com
Maintainer: Thomas Cokelaer
Maintainer-email: cokelaer@gmail.com
License: BSD
Download-URL: http://github.com/biokit/biokit
Keywords: corrplot,heatmap
Platform: Linux
Platform: Unix
Platform: MacOsX
Platform: Windows
Classifier: Development Status :: 1 - Planning
Classifier: Intended Audience :: Developers
Classifier: Intended Audience :: Science/Research
Classifier: License :: OSI Approved :: BSD License
Classifier: Operating System :: OS Independent
Classifier: Programming Language :: Python :: 3.7
Classifier: Programming Language :: Python :: 3.8
Classifier: Programming Language :: Python :: 3.9
Classifier: Topic :: Software Development :: Libraries :: Python Modules
Classifier: Topic :: Scientific/Engineering :: Bio-Informatics
Classifier: Topic :: Scientific/Engineering :: Information Analysis
Classifier: Topic :: Scientific/Engineering :: Mathematics
Classifier: Topic :: Scientific/Engineering :: Physics
License-File: LICENSE
